{
    "config": {
        "iso": "2020-09-21T09:51:37.647777",
        "timestamp": 1600681897.647777
    },
    "directory_structure": {
        "iso": "2020-09-21T09:51:37.782576",
        "timestamp": 1600681897.782576
    },
    "iana": {
        "iso": "2020-09-20T13:26:42.263481",
        "timestamp": 1600608402.263481
    },
    "psl": {
        "iso": "2020-09-20T13:26:42.461869",
        "timestamp": 1600608402.461869
    },
    "user_agents": {
        "iso": "2020-09-20T13:26:42.670005",
        "timestamp": 1600608402.670005
    }
}