{
    "config": {
        "iso": "2020-10-10T09:52:56.353018",
        "timestamp": 1602323576.353018
    },
    "directory_structure": {
        "iso": "2020-10-10T09:52:57.152941",
        "timestamp": 1602323577.152941
    },
    "iana": {
        "iso": "2020-10-10T09:52:56.600757",
        "timestamp": 1602323576.600757
    },
    "psl": {
        "iso": "2020-10-10T09:52:56.800159",
        "timestamp": 1602323576.800159
    },
    "user_agents": {
        "iso": "2020-10-10T09:52:57.012659",
        "timestamp": 1602323577.012659
    }
}