{
    "config": {
        "iso": "2020-10-11T21:51:14.216092",
        "timestamp": 1602453074.216092
    },
    "directory_structure": {
        "iso": "2020-10-11T21:51:14.423842",
        "timestamp": 1602453074.423842
    },
    "iana": {
        "iso": "2021-09-17T01:13:39.171388",
        "timestamp": 1631841219.171388
    },
    "psl": {
        "iso": "2021-09-17T01:13:39.206334",
        "timestamp": 1631841219.206334
    },
    "user_agents": {
        "iso": "2021-09-17T01:13:39.236635",
        "timestamp": 1631841219.236635
    }
}