[
    {
        "checker_type": "AVAILABILITY",
        "destination": "mobile.list",
        "hash": "94b4a404ff2f8a60510d6703620551efecf490a26232a8031d35269c",
        "line_number": 1064,
        "output_dir": "/home/runner/work/porn-records/porn-records/active_domains/output/mobile.list",
        "previous_hash": "94b4a404ff2f8a60510d6703620551efecf490a26232a8031d35269c",
        "session_id": "238c5b021ee31319076f74ba",
        "source": "submit_here/adult.mypdns.cloud/mobile.list",
        "subject": "submit_here/adult.mypdns.cloud/mobile.list",
        "subject_type": "domain",
        "type": "file"
    }
]