[
    {
        "checker_type": "AVAILABILITY",
        "destination": "wildcard.list",
        "hash": "50786485b820c846a3713cdbc3ccada1c8a5ad8e42ac6c6909f4a537",
        "line_number": 2484,
        "output_dir": "/home/runner/work/porn-records/porn-records/active_domains/output/wildcard.list",
        "previous_hash": "50786485b820c846a3713cdbc3ccada1c8a5ad8e42ac6c6909f4a537",
        "session_id": "b4385b471905e790204939a5",
        "source": "submit_here/adult.mypdns.cloud/wildcard.list",
        "subject": "submit_here/adult.mypdns.cloud/wildcard.list",
        "subject_type": "domain",
        "type": "file"
    }
]