[
    {
        "checker_type": "AVAILABILITY",
        "destination": "wildcard.list",
        "hash": "bc9441eecdebb0215d2e7ce343955a7cb4a98888bca2e1e22a08757e",
        "line_number": 2709,
        "output_dir": "/home/runner/work/porn-records/porn-records/active_domains/output/wildcard.list",
        "previous_hash": "bc9441eecdebb0215d2e7ce343955a7cb4a98888bca2e1e22a08757e",
        "session_id": "e80d5ac2c4660d996151f9a8",
        "source": "submit_here/adult.mypdns.cloud/wildcard.list",
        "subject": "submit_here/adult.mypdns.cloud/wildcard.list",
        "subject_type": "domain",
        "type": "file"
    }
]