[
    {
        "checker_type": "AVAILABILITY",
        "destination": "wildcard.list",
        "hash": "9ca3784b862e3cb32c1563e6057b303def05f135706e0a658bca1860",
        "line_number": 2470,
        "output_dir": "/home/runner/work/porn-records/porn-records/active_domains/output/wildcard.list",
        "previous_hash": "9ca3784b862e3cb32c1563e6057b303def05f135706e0a658bca1860",
        "session_id": "9791003b86fb67112ee33d97",
        "source": "submit_here/adult.mypdns.cloud/wildcard.list",
        "subject": "submit_here/adult.mypdns.cloud/wildcard.list",
        "subject_type": "domain",
        "type": "file"
    }
]