[
    {
        "checker_type": "AVAILABILITY",
        "destination": "wildcard.list",
        "hash": "ed6fa66af26f6fa72fd029f662c209368199902f2e8700309810046d",
        "line_number": 2556,
        "output_dir": "/home/runner/work/porn-records/porn-records/active_domains/output/wildcard.list",
        "previous_hash": "ed6fa66af26f6fa72fd029f662c209368199902f2e8700309810046d",
        "session_id": "c118bbc8950c41ffc597fff8",
        "source": "submit_here/adult.mypdns.cloud/wildcard.list",
        "subject": "submit_here/adult.mypdns.cloud/wildcard.list",
        "subject_type": "domain",
        "type": "file"
    }
]